pip_package/__init__.py
pip_package/__main__.py
pip_package/a.py
pip_package/b.py
pip_package-0.3.dist-info/METADATA
pip_package-0.3.dist-info/WHEEL
pip_package-0.3.dist-info/entry_points.txt
pip_package-0.3.dist-info/top_level.txt
pip_package-0.3.dist-info/RECORD
