Metadata-Version: 2.1
Name: pip-package
Version: 0.3
Summary: build a pip package
Home-page: https://github.com/bfreiber/build-a-pip-package
Author: bfreiber
Author-email: freiberg.brandon@gmail.com
License: MIT
Platform: UNKNOWN
